CHANGELOG.rst
MANIFEST.in
README.rst
setup.py
django_funky_sheets.egg-info/PKG-INFO
django_funky_sheets.egg-info/SOURCES.txt
django_funky_sheets.egg-info/dependency_links.txt
django_funky_sheets.egg-info/requires.txt
django_funky_sheets.egg-info/top_level.txt
examples/__init__.py
examples/admin.py
examples/apps.py
examples/models.py
examples/tests.py
examples/urls.py
examples/views.py
examples/migrations/0001_initial.py
examples/migrations/__init__.py
funky_sheets/__init__.py
funky_sheets/apps.py
funky_sheets/formsets.py
funky_sheets/tests.py
funky_sheets/__pycache__/__init__.cpython-37.pyc
funky_sheets/__pycache__/formsets.cpython-37.pyc
funky_sheets/static/css/handsontable.full.min.css
funky_sheets/static/js/handsontable.full.min.js
funky_sheets/static/js/jquery-3.3.1.min.js
funky_sheets/templates/hot/errors.html
funky_sheets/templates/hot/hot.html
funky_sheets/templatetags/__init__.py
funky_sheets/templatetags/funky_sheets_tags.py
funky_sheets/templatetags/__pycache__/__init__.cpython-37.pyc
funky_sheets/templatetags/__pycache__/funky_sheets_tags.cpython-37.pyc
setup/__init__.py
setup/settings.py
setup/urls.py
setup/wsgi.py